{"cameraMode":{"drawMode":0,"name":"Shaded","section":"Shading Mode"},"sceneLighting":false,"audioPlay":false,"sceneViewState":{"m_AlwaysRefresh":false,"showFog":true,"showSkybox":false,"showFlares":true,"showImageEffects":true,"showParticleSystems":true,"showVisualEffectGraphs":true,"m_FxEnabled":true},"in2DMode":false,"pivot":{"x":-1.0,"y":0.0,"z":0.0},"rotation":{"x":0.6865980625152588,"y":0.0004786339704878628,"z":-0.0008625235641375184,"w":0.7277448177337647},"size":0.4898979663848877,"orthographic":false}